LICENSE.txt
MANIFEST.in
README.rst
setup.py
django_nuages_tag/__init__.py
django_nuages_tag/models.py
django_nuages_tag/tests.py
django_nuages_tag/views.py
django_nuages_tag.egg-info/PKG-INFO
django_nuages_tag.egg-info/SOURCES.txt
django_nuages_tag.egg-info/dependency_links.txt
django_nuages_tag.egg-info/not-zip-safe
django_nuages_tag.egg-info/top_level.txt
django_nuages_tag/templatetags/__init__.py
django_nuages_tag/templatetags/django_nuages_tag.py