Metadata-Version: 1.0
Name: django-nuages-tag
Version: 0.1.0
Summary: A simple Django TemplateTag (named compute_tag_cloud) to help in the creation of tag clouds.
Home-page: https://github.com/niconoe/django-nuages-tag/
Author: Nicolas Noé
Author-email: nicolas@niconoe.eu
License: BSD licence, see LICENCE.txt
Platform: UNKNOWN
